nlpbook/__init__.py
nlpbook/_nbdev.py
nlpbook-1.0.0.dist-info/LICENSE
nlpbook-1.0.0.dist-info/METADATA
nlpbook-1.0.0.dist-info/WHEEL
nlpbook-1.0.0.dist-info/entry_points.txt
nlpbook-1.0.0.dist-info/top_level.txt
nlpbook-1.0.0.dist-info/RECORD
