Metadata-Version: 2.1
Name: nlpbook
Version: 1.0.0
Summary: Applied Natural Language Processing in the Enterprise - An O'Reilly Media Publication
Home-page: https://github.com/nlpbook/nlpbook/tree/main/
Author: Ankur A. Patel and Ajay Uppili Arasanipalai
Author-email: authors@appliednlpbook.com
License: MIT License
Keywords: nlp ai deep-learning
Platform: UNKNOWN
Classifier: Development Status :: 3 - Alpha
Classifier: Intended Audience :: Developers
Classifier: Natural Language :: English
Classifier: Programming Language :: Python :: 3.6
Classifier: Programming Language :: Python :: 3.7
Classifier: Programming Language :: Python :: 3.8
Classifier: License :: OSI Approved :: MIT License
Requires-Python: >=3.6
Requires-Dist: pip
Requires-Dist: packaging
Requires-Dist: fastai (>=2.3.1)
Requires-Dist: transformers
Requires-Dist: torchtext
Requires-Dist: pyspark
Requires-Dist: torch
Provides-Extra: dev
Requires-Dist: nbdev ; extra == 'dev'
Requires-Dist: fastrelease ; extra == 'dev'
Requires-Dist: anaconda-client ; extra == 'dev'
